field/__init__.py
field-0.2.0.data/data/man/man1/field.1.gz
field-0.2.0.dist-info/METADATA
field-0.2.0.dist-info/WHEEL
field-0.2.0.dist-info/entry_points.txt
field-0.2.0.dist-info/DESCRIPTION.rst
field-0.2.0.dist-info/RECORD
field-0.2.0.dist-info/top_level.txt
field-0.2.0.dist-info/metadata.json
