Metadata-Version: 2.0
Name: field
Version: 0.2.0
Summary: Extact fields from a file
Home-page: https://github.com/bramwelt/field
Author: Trevor Bramwell
Author-email: trevor@bramwell.net
License: GPLv3+
Platform: UNKNOWN
Classifier: Development Status :: 3 - Alpha
Classifier: Environment :: Console
Classifier: Intended Audience :: System Administrators
Classifier: License :: OSI Approved :: GNU General Public License v3 or later (GPLv3+)
Classifier: Operating System :: POSIX :: Linux
Classifier: Programming Language :: Python
Classifier: Programming Language :: Python :: 2.7
Classifier: Topic :: Text Processing :: Filters
